{
  "$schema": "https://ui.shadcn.com/schema/registry.json",
  "name": "rich-text-editor",
  "homepage": "https://github.com/abaktiar/rich-text-editor",
  "items": [
    {
      "name": "rich-text-editor",
      "type": "registry:block",
      "title": "Rich Text Editor",
      "description": "A modern, feature-rich text editor with slash commands, code blocks, tables, @mentions, callouts, toggles, and file attachments. Built with Tiptap 3.x and React 19.",
      "dependencies": [
        "@tanstack/react-virtual",
        "@tiptap/extension-bubble-menu",
        "@tiptap/extension-code-block-lowlight",
        "@tiptap/extension-color",
        "@tiptap/extension-highlight",
        "@tiptap/extension-image",
        "@tiptap/extension-link",
        "@tiptap/extension-placeholder",
        "@tiptap/extension-table",
        "@tiptap/extension-table-cell",
        "@tiptap/extension-table-header",
        "@tiptap/extension-table-row",
        "@tiptap/extension-task-item",
        "@tiptap/extension-task-list",
        "@tiptap/extension-text-align",
        "@tiptap/extension-text-style",
        "@tiptap/extension-typography",
        "@tiptap/extension-underline",
        "@tiptap/pm",
        "@tiptap/react",
        "@tiptap/starter-kit",
        "@tiptap/suggestion",
        "lowlight",
        "react-pdf",
        "tippy.js"
      ],
      "registryDependencies": ["button", "popover"],
      "files": [
        {
          "path": "src/components/ui/editor/editor.tsx",
          "type": "registry:component",
          "target": "components/ui/editor/editor.tsx"
        },
        {
          "path": "src/components/ui/editor/viewer.tsx",
          "type": "registry:component",
          "target": "components/ui/editor/viewer.tsx"
        },
        {
          "path": "src/components/ui/editor/toolbar.tsx",
          "type": "registry:component",
          "target": "components/ui/editor/toolbar.tsx"
        },
        {
          "path": "src/components/ui/editor/bubble-menu.tsx",
          "type": "registry:component",
          "target": "components/ui/editor/bubble-menu.tsx"
        },
        {
          "path": "src/components/ui/editor/command-menu.tsx",
          "type": "registry:component",
          "target": "components/ui/editor/command-menu.tsx"
        },
        {
          "path": "src/components/ui/editor/link-popover.tsx",
          "type": "registry:component",
          "target": "components/ui/editor/link-popover.tsx"
        },
        {
          "path": "src/components/ui/editor/table-controls.tsx",
          "type": "registry:component",
          "target": "components/ui/editor/table-controls.tsx"
        },
        {
          "path": "src/components/ui/editor/code-block.tsx",
          "type": "registry:component",
          "target": "components/ui/editor/code-block.tsx"
        },
        {
          "path": "src/components/ui/editor/callout.tsx",
          "type": "registry:component",
          "target": "components/ui/editor/callout.tsx"
        },
        {
          "path": "src/components/ui/editor/toggle.tsx",
          "type": "registry:component",
          "target": "components/ui/editor/toggle.tsx"
        },
        {
          "path": "src/components/ui/editor/file-attachment.tsx",
          "type": "registry:component",
          "target": "components/ui/editor/file-attachment.tsx"
        },
        {
          "path": "src/components/ui/editor/file-attachment-menu.tsx",
          "type": "registry:component",
          "target": "components/ui/editor/file-attachment-menu.tsx"
        },
        {
          "path": "src/components/ui/editor/file-preview-dialog.tsx",
          "type": "registry:component",
          "target": "components/ui/editor/file-preview-dialog.tsx"
        },
        {
          "path": "src/components/ui/editor/mention-list.tsx",
          "type": "registry:component",
          "target": "components/ui/editor/mention-list.tsx"
        },
        {
          "path": "src/components/ui/editor/mention-component.tsx",
          "type": "registry:component",
          "target": "components/ui/editor/mention-component.tsx"
        },
        {
          "path": "src/components/ui/editor/commands.ts",
          "type": "registry:lib",
          "target": "components/ui/editor/commands.ts"
        },
        {
          "path": "src/components/ui/editor/types.ts",
          "type": "registry:lib",
          "target": "components/ui/editor/types.ts"
        },
        {
          "path": "src/components/ui/editor/index.ts",
          "type": "registry:lib",
          "target": "components/ui/editor/index.ts"
        },
        {
          "path": "src/components/ui/editor/editor.css",
          "type": "registry:file",
          "target": "components/ui/editor/editor.css"
        },
        {
          "path": "src/components/ui/editor/extensions/index.ts",
          "type": "registry:lib",
          "target": "components/ui/editor/extensions/index.ts"
        },
        {
          "path": "src/components/ui/editor/extensions/code-block.ts",
          "type": "registry:lib",
          "target": "components/ui/editor/extensions/code-block.ts"
        },
        {
          "path": "src/components/ui/editor/extensions/slash-commands.ts",
          "type": "registry:lib",
          "target": "components/ui/editor/extensions/slash-commands.ts"
        },
        {
          "path": "src/components/ui/editor/extensions/callout.ts",
          "type": "registry:lib",
          "target": "components/ui/editor/extensions/callout.ts"
        },
        {
          "path": "src/components/ui/editor/extensions/toggle.ts",
          "type": "registry:lib",
          "target": "components/ui/editor/extensions/toggle.ts"
        },
        {
          "path": "src/components/ui/editor/extensions/table.ts",
          "type": "registry:lib",
          "target": "components/ui/editor/extensions/table.ts"
        },
        {
          "path": "src/components/ui/editor/extensions/file-attachment.ts",
          "type": "registry:lib",
          "target": "components/ui/editor/extensions/file-attachment.ts"
        },
        {
          "path": "src/components/ui/editor/extensions/mention-extension.ts",
          "type": "registry:lib",
          "target": "components/ui/editor/extensions/mention-extension.ts"
        },
        {
          "path": "src/components/ui/editor/extensions/mention-suggestion.ts",
          "type": "registry:lib",
          "target": "components/ui/editor/extensions/mention-suggestion.ts"
        },
        {
          "path": "src/components/ui/editor/plugins/index.ts",
          "type": "registry:lib",
          "target": "components/ui/editor/plugins/index.ts"
        },
        {
          "path": "src/components/ui/editor/plugins/file-upload.ts",
          "type": "registry:lib",
          "target": "components/ui/editor/plugins/file-upload.ts"
        },
        {
          "path": "src/components/ui/editor/plugins/mention.ts",
          "type": "registry:lib",
          "target": "components/ui/editor/plugins/mention.ts"
        }
      ]
    }
  ]
}
